LICENSE
MANIFEST.in
README.md
setup.py
wagtail_onboarding/__init__.py
wagtail_onboarding/apps.py
wagtail_onboarding/models.py
wagtail_onboarding/views.py
wagtail_onboarding/wagtail_hooks.py
wagtail_onboarding.egg-info/PKG-INFO
wagtail_onboarding.egg-info/SOURCES.txt
wagtail_onboarding.egg-info/dependency_links.txt
wagtail_onboarding.egg-info/not-zip-safe
wagtail_onboarding.egg-info/requires.txt
wagtail_onboarding.egg-info/top_level.txt
wagtail_onboarding/migrations/0001_initial.py
wagtail_onboarding/migrations/__init__.py
wagtail_onboarding/static/wagtail_onboarding/js/.gitignore
wagtail_onboarding/static/wagtail_onboarding/js/wagtail-onboarding.js
wagtail_onboarding/static_src/App.js
wagtail_onboarding/static_src/Utils.js
wagtail_onboarding/static_src/custom.d.ts
wagtail_onboarding/static_src/index.css
wagtail_onboarding/static_src/main.js
wagtail_onboarding/static_src/steps/EditView.js
wagtail_onboarding/static_src/steps/Home.js